Workbook

Sheet README
A1: Sales & Marketing Campaign Dashboard
A3: Author | B3: Syed Asfandyar Shah
A4: Purpose | B4: Track sales and compare how well each marketing campaign performs (revenue, cost per order, ROI).
A6: SAMPLE DATA | B6: All numbers in this workbook are made-up sample data generated for demonstration. Replace them with real data.
A8: How to use
A9: 1 | B9: Sales sheet: add or replace rows. Edit only the blue columns (Order ID, Date, Product, Region, Campaign, Units, Unit Price). Month and Revenue calculate automatically.
A10: 2 | B10: Campaigns sheet: edit the blue cells (Spend, Impressions, Clicks). Orders, Revenue, CTR, Cost per Order and ROI calculate automatically.
A11: 3 | B11: Dashboard sheet: KPIs, tables and charts update automatically. Product, region and month labels in blue can be changed to match your data.
A12: 4 | B12: Campaign names on the Sales sheet must match the Campaigns sheet exactly, otherwise they will not be counted.
A14: Colour key | B14: Blue text = input you can edit. Black text = formula, do not overwrite.
A15: Assumptions | B15: Revenue = Units x Unit Price. ROI = (Revenue - Spend) / Spend. Each order is attributed to exactly one campaign. 'Organic' means no paid campaign (Spend = 0, so ROI shows n/a). Overall ROI divides ALL revenue (including Organic) by paid spend, so it overstates what the ads alone earned.
A16: Skills shown | B16: Excel formulas (SUMIFS, COUNTIFS, IFERROR), conditional formatting, charts, data layout, documentation.

Sheet Dashboard
A1: Sales & Marketing Dashboard
A2: Sample data, January to June 2026
A3: KPI | B3: Value
A4: Total Revenue (Rs) | B4: =SUM(Sales!$I$2:$I$151) -> 2353600
A5: Total Units Sold | B5: =SUM(Sales!$G$2:$G$151) -> 551
A6: Total Orders | B6: =COUNTA(Sales!$A$2:$A$151) -> 150
A7: Average Order Value (Rs) | B7: =IFERROR(B4/B6,0) -> 15690.667
A8: Total Marketing Spend (Rs) | B8: =Campaigns!C10 -> 273000
A9: Overall ROI | B9: =Campaigns!J10 -> 7.6212454
A11: Product | B11: Units | C11: Revenue (Rs) | D11: % of Revenue
A12: Wireless Earbuds | B12: =SUMIFS(Sales!$G$2:$G$151,Sales!$D$2:$D$151,A12) -> 128 | C12: =SUMIFS(Sales!$I$2:$I$151,Sales!$D$2:$D$151,A12) -> 576000 | D12: =IFERROR(C12/$B$4,0) -> 0.24473148
A13: Smart Watch | B13: =SUMIFS(Sales!$G$2:$G$151,Sales!$D$2:$D$151,A13) -> 101 | C13: =SUMIFS(Sales!$I$2:$I$151,Sales!$D$2:$D$151,A13) -> 959500 | D13: =IFERROR(C13/$B$4,0) -> 0.40767335
A14: Power Bank | B14: =SUMIFS(Sales!$G$2:$G$151,Sales!$D$2:$D$151,A14) -> 119 | C14: =SUMIFS(Sales!$I$2:$I$151,Sales!$D$2:$D$151,A14) -> 380800 | D14: =IFERROR(C14/$B$4,0) -> 0.1617947
A15: Phone Case | B15: =SUMIFS(Sales!$G$2:$G$151,Sales!$D$2:$D$151,A15) -> 69 | C15: =SUMIFS(Sales!$I$2:$I$151,Sales!$D$2:$D$151,A15) -> 62100 | D15: =IFERROR(C15/$B$4,0) -> 0.026385112
A16: Laptop Stand | B16: =SUMIFS(Sales!$G$2:$G$151,Sales!$D$2:$D$151,A16) -> 134 | C16: =SUMIFS(Sales!$I$2:$I$151,Sales!$D$2:$D$151,A16) -> 375200 | D16: =IFERROR(C16/$B$4,0) -> 0.15941536
A18: Region | B18: Orders | C18: Revenue (Rs) | D18: % of Revenue
A19: Karachi | B19: =COUNTIFS(Sales!$E$2:$E$151,A19) -> 30 | C19: =SUMIFS(Sales!$I$2:$I$151,Sales!$E$2:$E$151,A19) -> 458100 | D19: =IFERROR(C19/$B$4,0) -> 0.194638
A20: Lahore | B20: =COUNTIFS(Sales!$E$2:$E$151,A20) -> 34 | C20: =SUMIFS(Sales!$I$2:$I$151,Sales!$E$2:$E$151,A20) -> 538100 | D20: =IFERROR(C20/$B$4,0) -> 0.22862848
A21: Islamabad | B21: =COUNTIFS(Sales!$E$2:$E$151,A21) -> 41 | C21: =SUMIFS(Sales!$I$2:$I$151,Sales!$E$2:$E$151,A21) -> 736200 | D21: =IFERROR(C21/$B$4,0) -> 0.31279742
A22: Peshawar | B22: =COUNTIFS(Sales!$E$2:$E$151,A22) -> 45 | C22: =SUMIFS(Sales!$I$2:$I$151,Sales!$E$2:$E$151,A22) -> 621200 | D22: =IFERROR(C22/$B$4,0) -> 0.2639361
A24: Month | B24: Orders | C24: Revenue (Rs)
A25: 2026-01 | B25: =COUNTIFS(Sales!$C$2:$C$151,A25) -> 17 | C25: =SUMIFS(Sales!$I$2:$I$151,Sales!$C$2:$C$151,A25) -> 287200
A26: 2026-02 | B26: =COUNTIFS(Sales!$C$2:$C$151,A26) -> 22 | C26: =SUMIFS(Sales!$I$2:$I$151,Sales!$C$2:$C$151,A26) -> 387000
A27: 2026-03 | B27: =COUNTIFS(Sales!$C$2:$C$151,A27) -> 25 | C27: =SUMIFS(Sales!$I$2:$I$151,Sales!$C$2:$C$151,A27) -> 340500
A28: 2026-04 | B28: =COUNTIFS(Sales!$C$2:$C$151,A28) -> 29 | C28: =SUMIFS(Sales!$I$2:$I$151,Sales!$C$2:$C$151,A28) -> 488300
A29: 2026-05 | B29: =COUNTIFS(Sales!$C$2:$C$151,A29) -> 36 | C29: =SUMIFS(Sales!$I$2:$I$151,Sales!$C$2:$C$151,A29) -> 556100
A30: 2026-06 | B30: =COUNTIFS(Sales!$C$2:$C$151,A30) -> 21 | C30: =SUMIFS(Sales!$I$2:$I$151,Sales!$C$2:$C$151,A30) -> 294500
A32: Campaign | B32: Revenue (Rs) | C32: Spend (Rs) | D32: ROI
A33: =Campaigns!A4 -> Instagram Ads | B33: =Campaigns!G4 -> 626100 | C33: =Campaigns!C4 -> 60000 | D33: =Campaigns!J4 -> 9.435
A34: =Campaigns!A5 -> Facebook Ads | B34: =Campaigns!G5 -> 410700 | C34: =Campaigns!C5 -> 45000 | D34: =Campaigns!J5 -> 8.1266667
A35: =Campaigns!A6 -> Google Search | B35: =Campaigns!G6 -> 489600 | C35: =Campaigns!C6 -> 70000 | D35: =Campaigns!J6 -> 5.9942857
A36: =Campaigns!A7 -> Email Newsletter | B36: =Campaigns!G7 -> 219800 | C36: =Campaigns!C7 -> 8000 | D36: =Campaigns!J7 -> 26.475
A37: =Campaigns!A8 -> Influencer Promo | B37: =Campaigns!G8 -> 326900 | C37: =Campaigns!C8 -> 90000 | D37: =Campaigns!J8 -> 2.6322222
A38: =Campaigns!A9 -> Organic | B38: =Campaigns!G9 -> 280500 | C38: =Campaigns!C9 -> 0 | D38: =Campaigns!J9 -> n/a

Sheet Sales
A1: Order ID | B1: Date | C1: Month | D1: Product | E1: Region | F1: Campaign | G1: Units | H1: Unit Price (Rs) | I1: Revenue (Rs) | K1: Blue = input, black = formula. Example row format: ORD-1001 | 15-Jan-2026 | Smart Watch | Karachi | Instagram Ads | 2 | 9500
A2: ORD-1001 | B2: 46053 | C2: =TEXT(B2,"yyyy-mm") -> 2026-01 | D2: Power Bank | E2: Karachi | F2: Organic | G2: 5 | H2: 3200 | I2: =G2*H2 -> 16000
A3: ORD-1002 | B3: 46182 | C3: =TEXT(B3,"yyyy-mm") -> 2026-06 | D3: Laptop Stand | E3: Peshawar | F3: Influencer Promo | G3: 5 | H3: 2800 | I3: =G3*H3 -> 14000
A4: ORD-1003 | B4: 46148 | C4: =TEXT(B4,"yyyy-mm") -> 2026-05 | D4: Laptop Stand | E4: Peshawar | F4: Facebook Ads | G4: 5 | H4: 2800 | I4: =G4*H4 -> 14000
A5: ORD-1004 | B5: 46043 | C5: =TEXT(B5,"yyyy-mm") -> 2026-01 | D5: Wireless Earbuds | E5: Islamabad | F5: Influencer Promo | G5: 4 | H5: 4500 | I5: =G5*H5 -> 18000
A6: ORD-1005 | B6: 46025 | C6: =TEXT(B6,"yyyy-mm") -> 2026-01 | D6: Phone Case | E6: Islamabad | F6: Instagram Ads | G6: 3 | H6: 900 | I6: =G6*H6 -> 2700
A7: ORD-1006 | B7: 46112 | C7: =TEXT(B7,"yyyy-mm") -> 2026-03 | D7: Power Bank | E7: Peshawar | F7: Organic | G7: 5 | H7: 3200 | I7: =G7*H7 -> 16000
A8: ORD-1007 | B8: 46186 | C8: =TEXT(B8,"yyyy-mm") -> 2026-06 | D8: Wireless Earbuds | E8: Islamabad | F8: Instagram Ads | G8: 5 | H8: 4500 | I8: =G8*H8 -> 22500
A9: ORD-1008 | B9: 46097 | C9: =TEXT(B9,"yyyy-mm") -> 2026-03 | D9: Power Bank | E9: Peshawar | F9: Instagram Ads | G9: 6 | H9: 3200 | I9: =G9*H9 -> 19200
A10: ORD-1009 | B10: 46203 | C10: =TEXT(B10,"yyyy-mm") -> 2026-06 | D10: Laptop Stand | E10: Islamabad | F10: Instagram Ads | G10: 6 | H10: 2800 | I10: =G10*H10 -> 16800
A11: ORD-1010 | B11: 46117 | C11: =TEXT(B11,"yyyy-mm") -> 2026-04 | D11: Power Bank | E11: Peshawar | F11: Google Search | G11: 4 | H11: 3200 | I11: =G11*H11 -> 12800
A12: ORD-1011 | B12: 46172 | C12: =TEXT(B12,"yyyy-mm") -> 2026-05 | D12: Laptop Stand | E12: Peshawar | F12: Organic | G12: 4 | H12: 2800 | I12: =G12*H12 -> 11200
A13: ORD-1012 | B13: 46152 | C13: =TEXT(B13,"yyyy-mm") -> 2026-05 | D13: Laptop Stand | E13: Peshawar | F13: Facebook Ads | G13: 5 | H13: 2800 | I13: =G13*H13 -> 14000
... A151: ORD-1150 | B151: 46077 | C151: =TEXT(B151,"yyyy-mm") -> 2026-02 | D151: Power Bank | E151: Lahore | F151: Google Search | G151: 4 | H151: 3200 | I151: =G151*H151 -> 12800

Sheet Campaigns
A1: Campaign Performance
A3: Campaign | B3: Channel | C3: Spend (Rs) | D3: Impressions | E3: Clicks | F3: Orders | G3: Revenue (Rs) | H3: CTR | I3: Cost per Order (Rs) | J3: ROI
A4: Instagram Ads | B4: Social | C4: 60000 | D4: 420000 | E4: 9800 | F4: =COUNTIFS(Sales!$F$2:$F$151,A4) -> 42 | G4: =SUMIFS(Sales!$I$2:$I$151,Sales!$F$2:$F$151,A4) -> 626100 | H4: =IFERROR(E4/D4,"n/a") -> 0.023333333 | I4: =IFERROR(C4/F4,"n/a") -> 1428.5714 | J4: =IF(C4=0,"n/a",(G4-C4)/C4) -> 9.435
A5: Facebook Ads | B5: Social | C5: 45000 | D5: 380000 | E5: 7100 | F5: =COUNTIFS(Sales!$F$2:$F$151,A5) -> 27 | G5: =SUMIFS(Sales!$I$2:$I$151,Sales!$F$2:$F$151,A5) -> 410700 | H5: =IFERROR(E5/D5,"n/a") -> 0.018684211 | I5: =IFERROR(C5/F5,"n/a") -> 1666.6667 | J5: =IF(C5=0,"n/a",(G5-C5)/C5) -> 8.1266667
A6: Google Search | B6: Search | C6: 70000 | D6: 210000 | E6: 11500 | F6: =COUNTIFS(Sales!$F$2:$F$151,A6) -> 29 | G6: =SUMIFS(Sales!$I$2:$I$151,Sales!$F$2:$F$151,A6) -> 489600 | H6: =IFERROR(E6/D6,"n/a") -> 0.054761905 | I6: =IFERROR(C6/F6,"n/a") -> 2413.7931 | J6: =IF(C6=0,"n/a",(G6-C6)/C6) -> 5.9942857
A7: Email Newsletter | B7: Email | C7: 8000 | D7: 60000 | E7: 3900 | F7: =COUNTIFS(Sales!$F$2:$F$151,A7) -> 17 | G7: =SUMIFS(Sales!$I$2:$I$151,Sales!$F$2:$F$151,A7) -> 219800 | H7: =IFERROR(E7/D7,"n/a") -> 0.065 | I7: =IFERROR(C7/F7,"n/a") -> 470.58824 | J7: =IF(C7=0,"n/a",(G7-C7)/C7) -> 26.475
A8: Influencer Promo | B8: Influencer | C8: 90000 | D8: 550000 | E8: 8200 | F8: =COUNTIFS(Sales!$F$2:$F$151,A8) -> 18 | G8: =SUMIFS(Sales!$I$2:$I$151,Sales!$F$2:$F$151,A8) -> 326900 | H8: =IFERROR(E8/D8,"n/a") -> 0.014909091 | I8: =IFERROR(C8/F8,"n/a") -> 5000 | J8: =IF(C8=0,"n/a",(G8-C8)/C8) -> 2.6322222
A9: Organic | B9: None | C9: 0 | D9: 0 | E9: 0 | F9: =COUNTIFS(Sales!$F$2:$F$151,A9) -> 17 | G9: =SUMIFS(Sales!$I$2:$I$151,Sales!$F$2:$F$151,A9) -> 280500 | H9: =IFERROR(E9/D9,"n/a") -> n/a | I9: =IFERROR(C9/F9,"n/a") -> 0 | J9: =IF(C9=0,"n/a",(G9-C9)/C9) -> n/a
A10: TOTAL | C10: =SUM(C4:C9) -> 273000 | D10: =SUM(D4:D9) -> 1620000 | E10: =SUM(E4:E9) -> 40500 | F10: =SUM(F4:F9) -> 150 | G10: =SUM(G4:G9) -> 2353600 | H10: =IFERROR(E10/D10,"n/a") -> 0.025 | I10: =IFERROR(C10/F10,"n/a") -> 1820 | J10: =IF(C10=0,"n/a",(G10-C10)/C10) -> 7.6212454
A12: Spend, impressions and clicks are sample figures entered by the author (blue). Orders and revenue are calculated from the Sales sheet.
